LICENSE
README.md
setup.py
wise_topic/__init__.py
wise_topic.egg-info/PKG-INFO
wise_topic.egg-info/SOURCES.txt
wise_topic.egg-info/dependency_links.txt
wise_topic.egg-info/requires.txt
wise_topic.egg-info/top_level.txt
wise_topic/classifier/__init__.py
wise_topic/classifier/classifier.py
wise_topic/classifier/prompts.py
wise_topic/cluster/__init__.py
wise_topic/cluster/balanced_sampling.py
wise_topic/cluster/clustering.py
wise_topic/cluster/embedders.py
wise_topic/cluster/plot.py
wise_topic/cluster/preprocessing.py
wise_topic/cluster/sample.py
wise_topic/topic/__init__.py
wise_topic/topic/classifier.py
wise_topic/topic/greedy.py
wise_topic/topic/topic_extractor.py